reathon/__init__.py
reathon/exceptions.py
reathon/helper.py
reathon/nodes.py
reathon-0.0.9.dist-info/METADATA
reathon-0.0.9.dist-info/WHEEL
reathon-0.0.9.dist-info/top_level.txt
reathon-0.0.9.dist-info/RECORD
