Metadata-Version: 2.4
Name: reathon
Version: 0.0.9
Summary: Construct REAPER projects in Python.
Home-page: https://github.com/jamesb93/reathon
Author: James Bradbury
Author-email: 
License: GLPv3+
Dynamic: author
Dynamic: description
Dynamic: description-content-type
Dynamic: home-page
Dynamic: license
Dynamic: summary
